fika
