Metadata-Version: 2.1
Name: fika
Version: 1.0.1
Summary: Automate Data Science Workflow from Exploratory Data Analysis to Model Deployment
Home-page: https://github.com/karthikraja95/fika
Author: Karthik Bhaskar
Author-email: karthikrajabk@gmail.com
License: GPL-3.0
Keywords: datascience,machinelearning,automation,analysis,automl,python,eda
Platform: UNKNOWN
Classifier: Programming Language :: Python :: 3.6
Classifier: Programming Language :: Python :: 3.7
Requires-Python: >= 3.6
Provides-Extra: ptmodels
